Metadata-Version: 2.4
Name: textract-supercog
Version: 1.6.5.post1
Summary: extract text from any document. no muss. no fuss.
Home-page: https://github.com/supercog-ai/textract
Download-URL: https://github.com/supercog-ai/textract/archives/master
Author: SuperCog AI (fork), Original author: Dean Malmgren
Author-email: your.email@example.com
License: MIT
Classifier: Development Status :: 5 - Production/Stable
Classifier: Intended Audience :: Developers
Classifier: License :: OSI Approved :: MIT License
Classifier: Programming Language :: Python :: 3
Classifier: Topic :: Text Processing
Classifier: Topic :: Text Processing :: Linguistic
Classifier: Topic :: Utilities
Requires-Python: >=3.6
License-File: LICENSE
Requires-Dist: argcomplete~=3.5
Requires-Dist: beautifulsoup4~=4.8
Requires-Dist: chardet~=5.2
Requires-Dist: docx2txt~=0.8
Requires-Dist: extract-msg<=0.29.0
Requires-Dist: pdfminer.six==20191110
Requires-Dist: python-pptx~=1.0
Requires-Dist: six~=1.17
Requires-Dist: SpeechRecognition~=3.11
Requires-Dist: xlrd~=2.0
Requires-Dist: openpyxl~=3.1
Provides-Extra: pocketsphinx
Requires-Dist: pocketsphinx==0.1.15; extra == "pocketsphinx"
Dynamic: author
Dynamic: author-email
Dynamic: classifier
Dynamic: description
Dynamic: description-content-type
Dynamic: download-url
Dynamic: home-page
Dynamic: license
Dynamic: license-file
Dynamic: provides-extra
Dynamic: requires-dist
Dynamic: requires-python
Dynamic: summary
